sharedflet/__init__.py
sharedflet/core.py
sharedflet/exceptions.py
sharedflet/utils.py
sharedpreferenceflet-1.1.0.dist-info/licenses/LICENSE
sharedpreferenceflet-1.1.0.dist-info/METADATA
sharedpreferenceflet-1.1.0.dist-info/WHEEL
sharedpreferenceflet-1.1.0.dist-info/top_level.txt
sharedpreferenceflet-1.1.0.dist-info/RECORD
