Metadata-Version: 2.4
Name: sharedpreferenceflet
Version: 1.1.0
Summary: Encrypted JSON-like Shared Preferences for Python
Home-page: https://github.com/AmirLouktaila/SharedPreferenceFlet
Author: Amir Louktila
Author-email: amir.louktila@gmail.com
Classifier: Programming Language :: Python :: 3
Classifier: Operating System :: OS Independent
Requires-Python: >=3.6
License-File: LICENSE
Requires-Dist: cryptography>=3.4.7
Dynamic: author
Dynamic: author-email
Dynamic: classifier
Dynamic: home-page
Dynamic: license-file
Dynamic: requires-dist
Dynamic: requires-python
Dynamic: summary
